VAPL/__init__.py
VAPL/main.py
VAPL/Modules/Web.py
VAPL/static/code.js
VAPL/static/mic_error.png
VAPL/static/mic_off.png
VAPL/static/mic_on.png
VAPL/static/showText.js
VAPL/static/speaker_error.png
VAPL/static/speaker_off.png
VAPL/static/speaker_on.png
VAPL/static/styles/mainpage.css
VAPL/templates/Executer.html
VAPL/templates/PageNotFound.html
VAPL/templates/docs.html
VAPL/templates/index.html
VAPL/templates/login.html
vapl-1.0.10.dist-info/licenses/LICENSE
vapl-1.0.10.dist-info/licenses/LICENSES
vapl-1.0.10.dist-info/METADATA
vapl-1.0.10.dist-info/WHEEL
vapl-1.0.10.dist-info/top_level.txt
vapl-1.0.10.dist-info/RECORD
