Metadata-Version: 2.4
Name: VAPL
Version: 1.0.10
Summary: VAPL - programming language to create voice assistants
Home-page: https://github.com/NotMEE12/VAPL
Author: NotMEE12
Author-email: legominefan@gmail.com
Classifier: Programming Language :: Python :: 3
Classifier: License :: OSI Approved :: GNU General Public License v3 or later (GPLv3+)
Classifier: Operating System :: OS Independent
Requires-Python: >=3.7
License-File: LICENSE
License-File: LICENSES
Dynamic: license-file
